escapy/__init__.py
escapy/scapy.py
escapy-0.0.1.dist-info/LICENSE.txt
escapy-0.0.1.dist-info/METADATA
escapy-0.0.1.dist-info/WHEEL
escapy-0.0.1.dist-info/top_level.txt
escapy-0.0.1.dist-info/RECORD
