Metadata-Version: 2.1
Name: escapy
Version: 0.0.1
Summary: this solve electrical circuits by symbolic way
Author-email: luisCorl <lui.corl.ing@hotmail.com>
Project-URL: Homepage, https://github.com/luisCorl/escapy
Project-URL: Issues, https://github.com/luisCorl/escapy
Classifier: Programming Language :: Python :: 3
Classifier: License :: OSI Approved :: GNU General Public License v3 (GPLv3)
Classifier: Operating System :: OS Independent
Requires-Python: >=3.4
License-File: LICENSE.txt
